{
  "employees": [
    {
      "name": "Anant Rawat",
      "userName": "Montu",
      "email": "anant.rawat@gmail.com",
      "number": "1111222255",
      "password": "123456",
      "id": 1
    },
    {
      "name": "gaurav",
      "userName": "rawatgaurav2",
      "email": "rawatgaurav2@gmail.com",
      "number": "9412971220",
      "password": "Gaurav2@",
      "id": 3
    },
    {
      "name": "Anant Rawat",
      "userName": "Mon2",
      "email": "anant5.rawat5@gmail.com",
      "number": "8888888888",
      "password": "123456",
      "id": 4
    }
  ],
  "userTasks": []
}